[
  {
    "account": "Travel & Entertainment",
    "account_type": "OpEx",
    "department": "Sales",
    "period": "2024-04",
    "budget": "$9,240",
    "actual": "$14,512",
    "variance_amt": "$+5,272",
    "variance_pct": "+57.1%",
    "severity": "CRITICAL",
    "direction": "OVER_BUDGET",
    "flag_type": "STATISTICAL"
  },
  {
    "account": "Marketing & Advertising",
    "account_type": "OpEx",
    "department": "Marketing",
    "period": "2024-07",
    "budget": "$86,450",
    "actual": "$124,481",
    "variance_amt": "$+38,031",
    "variance_pct": "+44.0%",
    "severity": "CRITICAL",
    "direction": "OVER_BUDGET",
    "flag_type": "STATISTICAL"
  },
  {
    "account": "Marketing & Advertising",
    "account_type": "OpEx",
    "department": "Marketing",
    "period": "2024-08",
    "budget": "$79,800",
    "actual": "$112,908",
    "variance_amt": "$+33,108",
    "variance_pct": "+41.5%",
    "severity": "CRITICAL",
    "direction": "OVER_BUDGET",
    "flag_type": "STATISTICAL"
  },
  {
    "account": "Cloud Infrastructure Costs",
    "account_type": "COGS",
    "department": "Engineering",
    "period": "2024-10",
    "budget": "$47,500",
    "actual": "$62,782",
    "variance_amt": "$+15,282",
    "variance_pct": "+32.2%",
    "severity": "CRITICAL",
    "direction": "OVER_BUDGET",
    "flag_type": "RULE_BASED"
  },
  {
    "account": "Professional Services Revenue",
    "account_type": "Revenue",
    "department": "Sales",
    "period": "2024-10",
    "budget": "$124,200",
    "actual": "$158,994",
    "variance_amt": "$+34,794",
    "variance_pct": "+28.0%",
    "severity": "HIGH",
    "direction": "BEAT",
    "flag_type": "STATISTICAL"
  },
  {
    "account": "Product Revenue - SaaS",
    "account_type": "Revenue",
    "department": "Sales",
    "period": "2024-08",
    "budget": "$467,500",
    "actual": "$358,093",
    "variance_amt": "$-109,407",
    "variance_pct": "-23.4%",
    "severity": "HIGH",
    "direction": "MISS",
    "flag_type": "RULE_BASED"
  },
  {
    "account": "Marketing & Advertising",
    "account_type": "OpEx",
    "department": "Marketing",
    "period": "2024-09",
    "budget": "$73,150",
    "actual": "$89,684",
    "variance_amt": "$+16,534",
    "variance_pct": "+22.6%",
    "severity": "HIGH",
    "direction": "OVER_BUDGET",
    "flag_type": "STATISTICAL"
  },
  {
    "account": "Product Revenue - SaaS",
    "account_type": "Revenue",
    "department": "Sales",
    "period": "2024-07",
    "budget": "$459,000",
    "actual": "$366,385",
    "variance_amt": "$-92,615",
    "variance_pct": "-20.2%",
    "severity": "HIGH",
    "direction": "MISS",
    "flag_type": "RULE_BASED"
  },
  {
    "account": "Depreciation & Amortization",
    "account_type": "OpEx",
    "department": "Customer Success",
    "period": "2024-06",
    "budget": "$3,750",
    "actual": "$3,379",
    "variance_amt": "$-371",
    "variance_pct": "-9.9%",
    "severity": "LOW",
    "direction": "UNDER_BUDGET",
    "flag_type": "STATISTICAL"
  },
  {
    "account": "Rent & Facilities",
    "account_type": "OpEx",
    "department": "Marketing",
    "period": "2024-08",
    "budget": "$5,250",
    "actual": "$5,764",
    "variance_amt": "$+514",
    "variance_pct": "+9.8%",
    "severity": "LOW",
    "direction": "OVER_BUDGET",
    "flag_type": "STATISTICAL"
  },
  {
    "account": "Professional Services COGS",
    "account_type": "COGS",
    "department": "Engineering",
    "period": "2024-01",
    "budget": "$19,800",
    "actual": "$21,633",
    "variance_amt": "$+1,833",
    "variance_pct": "+9.3%",
    "severity": "LOW",
    "direction": "OVER_BUDGET",
    "flag_type": "STATISTICAL"
  },
  {
    "account": "Software & Tools",
    "account_type": "OpEx",
    "department": "G&A",
    "period": "2024-04",
    "budget": "$1,800",
    "actual": "$1,634",
    "variance_amt": "$-166",
    "variance_pct": "-9.2%",
    "severity": "LOW",
    "direction": "UNDER_BUDGET",
    "flag_type": "STATISTICAL"
  }
]